python_quilt-1.0.data/scripts/pquilt
python_quilt-1.0.dist-info/DESCRIPTION.rst
python_quilt-1.0.dist-info/METADATA
python_quilt-1.0.dist-info/RECORD
python_quilt-1.0.dist-info/WHEEL
python_quilt-1.0.dist-info/metadata.json
python_quilt-1.0.dist-info/top_level.txt
quilt/__init__.py
quilt/add.py
quilt/backup.py
quilt/command.py
quilt/db.py
quilt/delete.py
quilt/error.py
quilt/new.py
quilt/patch.py
quilt/patchimport.py
quilt/pop.py
quilt/push.py
quilt/refresh.py
quilt/revert.py
quilt/signals.py
quilt/utils.py
quilt/cli/__init__.py
quilt/cli/add.py
quilt/cli/applied.py
quilt/cli/delete.py
quilt/cli/edit.py
quilt/cli/meta.py
quilt/cli/new.py
quilt/cli/next.py
quilt/cli/parser.py
quilt/cli/patchimport.py
quilt/cli/pop.py
quilt/cli/previous.py
quilt/cli/push.py
quilt/cli/refresh.py
quilt/cli/revert.py
quilt/cli/series.py
quilt/cli/top.py
quilt/cli/unapplied.py
