Metadata-Version: 2.0
Name: python-quilt
Version: 1.0
Summary: A quilt patch system implementation in Python
Home-page: http://github.com/bjoernricks/python-quilt
Author: Björn Ricks
Author-email: bjoern.ricks@gmail.com
License: MIT
Keywords: patch quilt python cli
Platform: UNKNOWN
Classifier: Development Status :: 4 - Beta
Classifier: Environment :: Console
Classifier: Intended Audience :: Developers
Classifier: Intended Audience :: System Administrators
Classifier: License :: OSI Approved :: MIT License
Classifier: Programming Language :: Python
Classifier: Programming Language :: Python :: 2.7
Classifier: Programming Language :: Python :: 3.2
Classifier: Programming Language :: Python :: 3.3
Classifier: Programming Language :: Python :: 3.4
Classifier: Programming Language :: Python :: 3.5
Classifier: Programming Language :: Python :: 3.6
Classifier: Topic :: Software Development :: Build Tools
Classifier: Topic :: System :: Software Distribution
Classifier: Topic :: Utilities
Requires-Dist: six
